mdlp_discretization-0.3.3.dist-info/RECORD
mdlp_discretization-0.3.3.dist-info/WHEEL
mdlp_discretization-0.3.3.dist-info/top_level.txt
mdlp_discretization-0.3.3.dist-info/METADATA
mdlp/_mdlp.cpython-36m-i386-linux-gnu.so
mdlp/__init__.py
mdlp/discretization.py
