Metadata-Version: 2.1
Name: mdlp-discretization
Version: 0.3.3
Summary: 
Requires-Dist: numpy (>=1.11.2)
Requires-Dist: scipy (>=0.18.1)
Requires-Dist: scikit-learn (>=0.18.1)
